playlistgen/__init__.py
playlistgen/playlist.py
playlistgen-1.3.0.dist-info/entry_points.txt
playlistgen-1.3.0.dist-info/WHEEL
playlistgen-1.3.0.dist-info/METADATA
playlistgen-1.3.0.dist-info/RECORD
