Metadata-Version: 2.1
Name: playlistgen
Version: 1.3.0
Summary: Hobby project to generate vlc playlists
License: MIT
Author: Arslan
Author-email: rslnkrmt2552@gmail.com
Requires-Python: >=3.7,<4.0
Classifier: License :: OSI Approved :: MIT License
Classifier: Programming Language :: Python :: 3
Classifier: Programming Language :: Python :: 3.7
Requires-Dist: Click (>=7.0,<8.0)
Requires-Dist: lxml (>=4.3,<5.0)
Requires-Dist: moviepy (>=1.0,<2.0)
